thermo_metaextractor/__init__.py
thermo_metaextractor/extractor.py
thermo_metaextractor/utils.py
thermo_metaextractor-0.1.0.dist-info/METADATA
thermo_metaextractor-0.1.0.dist-info/WHEEL
thermo_metaextractor-0.1.0.dist-info/top_level.txt
thermo_metaextractor-0.1.0.dist-info/RECORD
